vmware_vspc-0.0.3.dist-info/DESCRIPTION.rst
vmware_vspc-0.0.3.dist-info/METADATA
vmware_vspc-0.0.3.dist-info/RECORD
vmware_vspc-0.0.3.dist-info/WHEEL
vmware_vspc-0.0.3.dist-info/entry_points.txt
vmware_vspc-0.0.3.dist-info/metadata.json
vmware_vspc-0.0.3.dist-info/pbr.json
vmware_vspc-0.0.3.dist-info/top_level.txt
vspc/__init__.py
vspc/async_telnet.py
vspc/server.py
vspc/tests/__init__.py
vspc/tests/test_server.py
